pyclipdrop/__init__.py
pyclipdrop/client.py
pyclipdrop/exceptions.py
pyclipdrop/io_file_handlers/__init__.py
pyclipdrop/io_file_handlers/input_file_handler.py
pyclipdrop/io_file_handlers/output_file_handler.py
pyclipdrop/settings.py
pyclipdrop/utilities/__init__.py
pyclipdrop/utilities/extractors.py
pyclipdrop/utilities/validators.py
pyclipdrop-1.0.1.dist-info/LICENSE
pyclipdrop-1.0.1.dist-info/METADATA
pyclipdrop-1.0.1.dist-info/WHEEL
pyclipdrop-1.0.1.dist-info/RECORD
