Metadata-Version: 2.1
Name: pyclipdrop
Version: 1.0.1
Summary: The Python SDK for the Clipdrop API.
Author: Minura Punchihewa
Author-email: minurapunchihewa17@gmail.com
Requires-Python: >=3.8
Classifier: Programming Language :: Python :: 3
Classifier: Programming Language :: Python :: 3.8
Classifier: Programming Language :: Python :: 3.9
Classifier: Programming Language :: Python :: 3.10
Classifier: Programming Language :: Python :: 3.11
Requires-Dist: pydantic-settings (>=2.2.1,<3.0.0)
Requires-Dist: requests (>=2.31.0,<3.0.0)
